LICENSE.txt
MANIFEST.in
README.md
setup.py
srambler.py
srambler_tests.py
srambler.egg-info/PKG-INFO
srambler.egg-info/SOURCES.txt
srambler.egg-info/dependency_links.txt
srambler.egg-info/top_level.txt