Metadata-Version: 1.0
Name: srambler
Version: 1.0.0
Summary: Helps with sanitizing data.
Home-page: https://github.com/polera/srambler
Author: James Polera
Author-email: james@uncryptic.com
License: BSD
Keywords: data,text,processing,sanitize,scramble
Platform: UNKNOWN
Classifier: Development Status :: 5 - Production/Stable
Classifier: Intended Audience :: Developers
Classifier: Natural Language :: English
Classifier: License :: OSI Approved :: BSD License
Classifier: Programming Language :: Python
Classifier: Programming Language :: Python :: 2.6
Classifier: Programming Language :: Python :: 2.7
Classifier: Programming Language :: Python :: 3.2
Classifier: Programming Language :: Python :: 3.3
